colorful-stubs/METADATA.toml
colorful-stubs/__init__.pyi
colorful-stubs/ansi.pyi
colorful-stubs/colors.pyi
colorful-stubs/core.pyi
colorful-stubs/py.typed
colorful-stubs/styles.pyi
colorful-stubs/terminal.pyi
colorful-stubs/utils.pyi
types_colorful-0.5.0.20251108.dist-info/licenses/LICENSE
types_colorful-0.5.0.20251108.dist-info/METADATA
types_colorful-0.5.0.20251108.dist-info/WHEEL
types_colorful-0.5.0.20251108.dist-info/top_level.txt
types_colorful-0.5.0.20251108.dist-info/RECORD
